shulker/__init__.py
shulker/components/Block.py
shulker/components/BlockCoordinates.py
shulker/components/BlockHandler.py
shulker/components/BlockState.py
shulker/components/BlockZone.py
shulker/components/Coordinates.py
shulker/components/Entity.py
shulker/components/NBT.py
shulker/components/TargetSelector.py
shulker/components/Zone.py
shulker/components/__init__.py
shulker/components/test/__init__.py
shulker/components/test/test_Block.py
shulker/components/test/test_BlockCoordinates.py
shulker/components/test/test_BlockHandler.py
shulker/components/test/test_BlockState.py
shulker/components/test/test_BlockZone.py
shulker/components/test/test_Coordinates.py
shulker/components/test/test_Entity.py
shulker/components/test/test_NBT.py
shulker/components/test/test_TargetSelector.py
shulker/components/test/test_Zone.py
shulker/functions/__init__.py
shulker/functions/_set_text.py
shulker/functions/base_functions.py
shulker/functions/color_picker.py
shulker/functions/default.py
shulker/functions/get_player_nbt.py
shulker/functions/set_gui.py
shulker/functions/set_image.py
shulker/functions/set_text.py
shulker/functions/update_entity.py
shulker/functions/mc_data/block_list.json
shulker/functions/mc_data/blocks_color.json
shulker/functions/mc_data/commands.json
shulker/functions/mc_data/palette.json
shulker/functions/mc_data/registries.json
shulker/functions/mc_data/set_text_data.json
shulker/metadata/data/block_list.json
shulker/metadata/data/commands.json
shulker/metadata/data/entity_nbt.json
shulker/metadata/data/registries.json
shulker/server/__init__.py
shulker/server/connect.py
shulker/server/create.py
shulker/server/ping.py
shulker/server/singleton.py
shulker-0.6.4.dist-info/LICENSE
shulker-0.6.4.dist-info/METADATA
shulker-0.6.4.dist-info/WHEEL
shulker-0.6.4.dist-info/top_level.txt
shulker-0.6.4.dist-info/RECORD
