Metadata-Version: 2.1
Name: shulker
Version: 0.6.4
Summary: A minecraft interface using RCON
Home-page: https://github.com/PortalHubYT/shulker
Author: PortalHubYT
Author-email: portalhub.business@gmail.com
License-File: LICENSE
Requires-Dist: docker
Requires-Dist: mctools
Requires-Dist: pillow
Requires-Dist: mcstatus
Requires-Dist: nbtlib ==1.12.1
Requires-Dist: jsbeautifier
Requires-Dist: selenium
